{
  "Entertainment": {
    "mean": 1202.58,
    "std": 725.27,
    "max": 1914.85
  },
  "Food & Drink": {
    "mean": 1039.04,
    "std": 580.83,
    "max": 1938.3
  },
  "Health & Fitness": {
    "mean": 851.61,
    "std": 589.25,
    "max": 1870.07
  },
  "Investment": {
    "mean": 1986.0,
    "std": 1080.7,
    "max": 3958.0
  },
  "Other": {
    "mean": 2949.29,
    "std": 1086.44,
    "max": 4009.0
  },
  "Rent": {
    "mean": 1149.93,
    "std": 734.84,
    "max": 1956.19
  },
  "Salary": {
    "mean": 836.65,
    "std": 567.19,
    "max": 1729.04
  },
  "Shopping": {
    "mean": 789.33,
    "std": 572.92,
    "max": 1929.08
  },
  "Travel": {
    "mean": 1179.99,
    "std": 646.37,
    "max": 1979.15
  },
  "Utilities": {
    "mean": 807.72,
    "std": 443.72,
    "max": 1475.58
  }
}